ahIOT/__init__.py
ahIOT-0.0.2.dist-info/METADATA
ahIOT-0.0.2.dist-info/WHEEL
ahIOT-0.0.2.dist-info/top_level.txt
ahIOT-0.0.2.dist-info/RECORD
